{
  "normal": ["fighting"],
  "fire": ["water", "ground", "rock"],
  "water": ["electric", "grass"],
  "electric": ["ground"],
  "grass": ["fire", "ice", "poison", "flying", "bug"],
  "ice": ["fire", "fighting", "rock", "steel"],
  "fighting": ["flying", "psychic", "fairy"],
  "poison": ["ground", "psychic"],
  "ground": ["water", "grass", "ice"],
  "flying": ["electric", "ice", "rock"],
  "psychic": ["bug", "ghost", "dark"],
  "bug": ["fire", "flying", "rock"],
  "rock": ["water", "grass", "fighting", "ground", "steel"],
  "ghost": ["ghost", "dark"],
  "dragon": ["ice", "dragon", "fairy"],
  "dark": ["fighting", "bug", "fairy"],
  "steel": ["fire", "fighting", "ground"],
  "fairy": ["poison", "steel"],
  "normal/fighting": ["fighting", "flying", "psychic", "fairy"],
  "normal/flying": ["electric", "ice", "rock"],
  "normal/poison": ["ground", "psychic"],
  "normal/ground": ["water", "grass", "ice", "fighting"],
  "normal/psychic": ["bug", "dark"],
  "normal/grass": ["fire", "ice", "fighting", "poison", "flying", "bug"],
  "normal/fairy": ["poison", "steel"],
  "normal/water": ["electric", "grass", "fighting"],
  "fire/fighting": ["water", "ground", "flying", "psychic"],
  "fire/flying": ["water", "electric", "rock"],
  "fire/poison": ["water", "ground", "psychic", "rock"],
  "fire/ground": ["water", "ground"],
  "fire/rock": ["water", "fighting", "ground"],
  "fire/bug": ["water", "flying", "rock"],
  "fire/steel": ["water", "fighting", "ground"],
  "fire/grass": ["poison", "flying", "rock"],
  "fire/psychic": ["water", "ground", "rock", "ghost", "dark"],
  "fire/ice": ["water", "fighting", "ground", "rock"],
  "fire/dragon": ["ground", "rock", "dragon"],
  "fire/dark": ["water", "fighting", "ground", "rock"],
  "fire/fairy": ["water", "poison", "ground", "rock"],
  "fire/ghost": ["water", "ground", "rock", "ghost", "dark"],
  "water/fighting": ["electric", "grass", "flying", "psychic", "fairy"],
  "water/flying": ["electric", "rock"],
  "water/poison": ["electric", "ground", "psychic"],
  "water/ground": ["grass"],
  "water/rock": ["electric", "grass", "fighting", "ground"],
  "water/bug": ["electric", "flying", "rock"],
  "water/steel": ["electric", "fighting", "ground"],
  "water/grass": ["poison", "flying", "bug"],
  "water/psychic": ["electric", "grass", "bug", "ghost", "dark"],
  "water/ice": ["electric", "grass", "fighting", "rock"],
  "water/dragon": ["dragon", "fairy"],
  "water/dark": ["electric", "grass", "fighting", "bug", "fairy"],
  "water/fairy": ["electric", "grass", "poison"],
  "water/ghost": ["electric", "grass", "ghost", "dark"],
  "electric/flying": ["ice", "rock"],
  "electric/poison": ["ground", "psychic"],
  "electric/steel": ["fire", "fighting", "ground"],
  "electric/grass": ["fire", "ice", "poison", "bug"],
  "electric/ice": ["fire", "fighting", "ground", "rock"],
  "electric/psychic": ["ground", "bug", "ghost", "dark"],
  "electric/bug": ["fire", "rock"],
  "electric/dragon": ["ice", "ground", "dragon", "fairy"],
  "electric/dark": ["fighting", "bug", "ground", "fairy"],
  "electric/fairy": ["poison", "ground"],
  "electric/ghost": ["ground", "ghost", "dark"],
  "electric/normal": ["fighting", "ground"],
  "grass/fighting": ["fire", "ice", "poison", "flying", "psychic", "fairy"],
  "grass/flying": ["fire", "ice", "poison", "flying", "rock"],
  "grass/poison": ["fire", "ice", "flying", "psychic"],
  "grass/ground": ["fire", "ice", "bug"],
  "grass/rock": ["ice", "fighting", "bug", "steel"],
  "grass/bug": ["fire", "ice", "poison", "flying", "rock"],
  "grass/steel": ["fire", "fighting"],
  "grass/psychic": ["fire", "ice", "poison", "flying", "bug", "ghost", "dark"],
  "grass/ice": ["fire", "fighting", "poison", "flying", "rock", "bug", "steel"],
  "grass/dragon": ["ice", "poison", "flying", "bug", "dragon", "fairy"],
  "grass/dark": ["fire", "ice", "fighting", "poison", "flying", "bug", "fairy"],
  "grass/fairy": ["fire", "ice", "poison", "flying", "steel"],
  "grass/ghost": ["fire", "ice", "poison", "flying", "ghost", "dark"],
  "ice/fighting": ["fire", "fighting", "flying", "psychic", "steel", "fairy"],
  "ice/flying": ["fire", "electric", "rock", "steel"],
  "ice/poison": ["fire", "ground", "psychic", "rock", "steel"],
  "ice/ground": ["fire", "water", "grass", "fighting", "steel"],
  "ice/rock": ["water", "grass", "fighting", "ground", "steel"],
  "ice/bug": ["fire", "flying", "rock", "steel"],
  "ice/steel": ["fire", "fighting"],
  "ice/psychic": ["fire", "bug", "rock", "ghost", "dark", "steel"],
  "ice/dragon": ["fighting", "rock", "dragon", "steel", "fairy"],
  "ice/dark": ["fire", "fighting", "bug", "rock", "steel", "fairy"],
  "ice/fairy": ["fire", "poison", "rock", "steel"],
  "ice/ghost": ["fire", "rock", "ghost", "dark", "steel"],
  "fighting/flying": ["electric", "ice", "flying", "psychic", "fairy"],
  "fighting/poison": ["ground", "flying", "psychic"],
  "fighting/ground": ["water", "grass", "ice", "flying", "psychic", "fairy"],
  "fighting/rock": ["water", "grass", "fighting", "ground", "psychic", "steel", "fairy"],
  "fighting/bug": ["fire", "flying", "psychic", "fairy"],
  "fighting/steel": ["fire", "fighting", "ground"],
  "fighting/psychic": ["flying", "ghost", "fairy"],
  "fighting/ice": ["fire", "fighting", "flying", "psychic", "steel", "fairy"],
  "fighting/dragon": ["ice", "flying", "psychic", "dragon", "fairy"],
  "fighting/dark": ["fighting", "flying", "fairy"],
  "fighting/fairy": ["poison", "flying", "psychic", "steel"],
  "fighting/ghost": ["flying", "psychic", "ghost", "fairy"],
  "poison/flying": ["electric", "ice", "psychic", "rock"],
  "poison/ground": ["water", "ice", "ground", "psychic"],
  "poison/rock": ["water", "ground", "psychic", "steel"],
  "poison/bug": ["fire", "flying", "psychic", "rock"],
  "poison/steel": ["fire", "ground"],
  "poison/psychic": ["ground", "ghost", "dark"],
  "poison/dragon": ["ice", "ground", "psychic", "dragon"],
  "poison/dark": ["ground"],
  "poison/fairy": ["ground", "psychic", "steel"],
  "poison/ghost": ["ground", "psychic", "ghost", "dark"],
  "ground/flying": ["ice", "water"],
  "ground/rock": ["water", "grass", "ice", "fighting", "ground", "steel"],
  "ground/bug": ["fire", "water", "ice", "flying"],
  "ground/steel": ["fire", "water", "fighting", "ground"],
  "ground/psychic": ["water", "grass", "ice", "bug", "ghost", "dark"],
  "ground/ice": ["fire", "water", "grass", "fighting", "steel"],
  "ground/dragon": ["ice", "dragon", "fairy"],
  "ground/dark": ["water", "grass", "ice", "fighting", "bug", "fairy"],
  "ground/fairy": ["water", "grass", "ice", "poison", "steel"],
  "ground/ghost": ["water", "grass", "ice", "ghost", "dark"],
  "flying/poison": ["electric", "ice", "psychic", "rock"],
  "flying/rock": ["water", "electric", "ice", "rock", "steel"],
  "flying/bug": ["fire", "electric", "ice", "flying", "rock"],
  "flying/steel": ["fire", "electric"],
  "flying/psychic": ["electric", "ice", "rock", "ghost", "dark"],
  "flying/ice": ["fire", "electric", "rock", "steel"],
  "flying/dragon": ["ice", "rock", "dragon", "fairy"],
  "flying/dark": ["electric", "ice", "rock", "fairy"],
  "flying/fairy": ["poison", "electric", "ice", "rock", "steel"],
  "flying/ghost": ["electric", "ice", "rock", "ghost", "dark"],
  "psychic/rock": ["water", "grass", "bug", "ghost", "dark", "steel"],
  "psychic/bug": ["fire", "flying", "rock", "ghost", "dark"],
  "psychic/steel": ["fire", "ground", "ghost", "dark"],
  "psychic/ice": ["fire", "bug", "rock", "ghost", "dark", "steel"],
  "psychic/dragon": ["ice", "bug", "ghost", "dragon", "dark", "fairy"],
  "psychic/dark": ["bug", "fairy"],
  "psychic/fairy": ["poison", "ghost", "steel"],
  "psychic/ghost": ["ghost", "dark"],
  "bug/rock": ["water", "rock", "steel"],
  "bug/steel": ["fire"],
  "bug/ice": ["fire", "flying", "rock", "steel"],
  "bug/dragon": ["ice", "flying", "rock", "dragon", "fairy"],
  "bug/dark": ["fire", "flying", "rock", "fairy"],
  "bug/fairy": ["fire", "poison", "flying", "rock", "steel"],
  "bug/ghost": ["fire", "flying", "rock", "ghost", "dark"],
  "rock/steel": ["water", "fighting", "ground"],
  "rock/psychic": ["water", "grass", "bug", "ghost", "dark", "steel"],
  "rock/ice": ["water", "grass", "fighting", "ground", "rock", "steel"],
  "rock/dragon": ["ice", "fighting", "ground", "dragon", "steel", "fairy"],
  "rock/dark": ["water", "grass", "fighting", "ground", "bug", "steel", "fairy"],
  "rock/fairy": ["water", "grass", "ground", "steel"],
  "rock/ghost": ["water", "grass", "ground", "ghost", "dark", "steel"],
  "ghost/steel": ["fire", "ground", "ghost", "dark"],
  "ghost/ice": ["fire", "rock", "ghost", "dark", "steel"],
  "ghost/dragon": ["ice", "ghost", "dragon", "dark", "fairy"],
  "ghost/dark": ["fairy"],
  "ghost/fairy": ["ghost", "steel"],
  "dragon/steel": ["fighting", "ground"],
  "dragon/ice": ["fighting", "rock", "dragon", "steel", "fairy"],
  "dragon/dark": ["ice", "fighting", "bug", "dragon", "fairy"],
  "dragon/fairy": ["poison", "steel", "fairy"],
  "dark/steel": ["fire", "fighting", "ground"],
  "dark/ice": ["fire", "fighting", "bug", "rock", "steel", "fairy"],
  "dark/fairy": ["poison", "steel", "fairy"],
  "steel/fairy": ["fire", "ground"],
  "steel/ice": ["fire", "fighting", "ground"],
  "steel/dragon": ["fighting", "ground"],
  "steel/ghost": ["fire", "ground", "ghost", "dark"],
  "steel/psychic": ["fire", "ground", "ghost", "dark"]
}
